README.md
setup.py
metaloop/__init__.py
metaloop/__version__.py
metaloop/exception.py
metaloop/client/__init__.py
metaloop/client/cloud_storage.py
metaloop/client/download_helper.py
metaloop/client/mds.py
metaloop/client/requests.py
metaloop/client/x_api.py
metaloop/dataset/__init__.py
metaloop/dataset/dataset.py
metaloop/dataset/exporter.py
metaloop/examples/__init__.py
metaloop/examples/algo_svc_test.py
metaloop/examples/call_model_convert.py
metaloop/examples/data_downloader.py
metaloop/examples/data_importer.py
metaloop/examples/dataset_manage.py
metaloop/examples/export_data.py
metaloop/examples/file_downloader.py
metaloop/examples/file_uploader.py
metaloop/examples/import_data.py
metaloop/examples/import_data_cos.py
metaloop/examples/iter_data.py
metaloop/examples/s3_file_download.py
metaloop/examples/send_notice.py
metaloop/examples/task_callback.py
metaloop/examples/update_calibset.py
metaloop/train_repo/__init__.py
metaloop/train_repo/train_repo_export.py
metaloop/train_repo/train_repo_import.py
metaloop/utils/__init__.py
metaloop/utils/file_helper.py
metaloop/utils/log.py
metaloop/utils/requests.py
metaloop/utils/video.py
metaloop/utils/zip.py
metaloop_python_sdk.egg-info/PKG-INFO
metaloop_python_sdk.egg-info/SOURCES.txt
metaloop_python_sdk.egg-info/dependency_links.txt
metaloop_python_sdk.egg-info/requires.txt
metaloop_python_sdk.egg-info/top_level.txt