Metadata-Version: 2.1
Name: metaloop-python-sdk
Version: 1.22.0
Summary: Deepglint Metaloop Python SDK
Home-page: http://data.deepglint.com/
Author: yuma
Author-email: yuma@deepglint.com
License: Apache License 2.0
Project-URL: Documentation, https://gitlab.deepglint.com/metaloop/metaloop-python-sdk
Project-URL: Source, https://gitlab.deepglint.com/metaloop/metaloop-python-sdk
Platform: UNKNOWN
Classifier: Development Status :: 5 - Production/Stable
Classifier: Intended Audience :: Developers
Classifier: Natural Language :: English
Classifier: License :: OSI Approved :: Apache Software License
Classifier: Programming Language :: Python
Classifier: Programming Language :: Python :: 3
Classifier: Programming Language :: Python :: 3.7
Classifier: Programming Language :: Python :: 3.8
Classifier: Programming Language :: Python :: 3.9
Classifier: Programming Language :: Python :: 3.10
Classifier: Programming Language :: Python :: 3.11
Requires-Python: >= 3.5
